codedoc_mcp/__init__.py
codedoc_mcp/__main__.py
codedoc_mcp/__version__.py
codedoc_mcp/app.py
codedoc_mcp/errors.py
codedoc_mcp/file.py
codedoc_mcp/log_config.py
codedoc_mcp/server.py
codedoc_mcp-0.1.0.dist-info/licenses/LICENSE
codedoc_mcp-0.1.0.dist-info/METADATA
codedoc_mcp-0.1.0.dist-info/WHEEL
codedoc_mcp-0.1.0.dist-info/entry_points.txt
codedoc_mcp-0.1.0.dist-info/top_level.txt
codedoc_mcp-0.1.0.dist-info/RECORD
