Metadata-Version: 2.4
Name: codedoc_mcp
Version: 0.1.0
Summary: Code analysis and documentation tool with MCP support
Home-page: https://github.com/aIFzzf/codedoc_mcp
Author: CodeDoc Team
Author-email: CodeDoc Team <neozheng2336@gmail.com>
License: MIT
Project-URL: Bug Reports, https://github.com/aIFzzf/codedoc_mcp/issues
Project-URL: Source, https://github.com/aIFzzf/codedoc_mcp
Project-URL: Documentation, https://github.com/aIFzzf/codedoc_mcp#readme
Keywords: code analysis,documentation,markdown,mermaid,diagram
Classifier: Development Status :: 3 - Alpha
Classifier: Intended Audience :: Developers
Classifier: License :: OSI Approved :: MIT License
Classifier: Programming Language :: Python :: 3
Classifier: Programming Language :: Python :: 3.8
Classifier: Programming Language :: Python :: 3.9
Classifier: Programming Language :: Python :: 3.10
Classifier: Topic :: Software Development :: Documentation
Classifier: Topic :: Software Development :: Libraries :: Python Modules
Classifier: Topic :: Software Development :: Code Generators
Requires-Python: >=3.8
License-File: LICENSE
Requires-Dist: loguru>=0.6.0
Requires-Dist: mcp>=1.0.0
Requires-Dist: regex>=2022.10.31
Requires-Dist: jinja2>=3.1.2
Requires-Dist: markdown>=3.4.3
Requires-Dist: httpx>=0.28.1
Dynamic: author
Dynamic: home-page
Dynamic: license-file
Dynamic: requires-python
